pepmast/__init__.py
pepmast-0.0.1.dist-info/METADATA
pepmast-0.0.1.dist-info/WHEEL
pepmast-0.0.1.dist-info/licenses/LICENSE
pepmast-0.0.1.dist-info/RECORD
