Metadata-Version: 2.4
Name: pepmast
Version: 0.0.1
Summary: Off-target prediction pipeline
Project-URL: homepage, https://github.com/Vivi-tran/PepMAST
Project-URL: source, https://github.com/Vivi-tran/PepMAST
Project-URL: issues, https://github.com/Vivi-tran/PepMAST/issues
Project-URL: documentation, https://Vivi-tran.github.io/PepMAST/
Author-email: Ngoc-Vi Nguyen TRAN <vi.tran@sund.ku.dk>
License-File: LICENSE
Classifier: License :: OSI Approved :: MIT License
Classifier: Operating System :: OS Independent
Classifier: Programming Language :: Python :: 3
Requires-Python: >=3.12
Requires-Dist: numpy==2.3.5
Requires-Dist: pandas>=2.2.0
Provides-Extra: all
Requires-Dist: pandas>=2.2.0; extra == 'all'
